README.rst
setup.py
OptlangHelper.egg-info/PKG-INFO
OptlangHelper.egg-info/SOURCES.txt
OptlangHelper.egg-info/dependency_links.txt
OptlangHelper.egg-info/requires.txt
OptlangHelper.egg-info/top_level.txt
optlanghelper/__init__.py
optlanghelper/optlanghelper.py