Metadata-Version: 2.1
Name: OptlangHelper
Version: 0.0.2
Summary: Python package for building Linear Programming models that are compatible with Optlang
Home-page: https://github.com/Freiburgermsu/OptlangHelper
Author: Andrew Freiburger
Author-email: afreiburger@anl.gov
License: UNKNOWN
Project-URL: Issues, https://github.com/Freiburgermsu/OptlangHelper/issues
Platform: UNKNOWN
Classifier: Development Status :: 3 - Alpha
Classifier: Topic :: Scientific/Engineering :: Bio-Informatics
Classifier: Intended Audience :: Science/Research
Classifier: Operating System :: OS Independent
Classifier: Programming Language :: Python :: 3.8
Classifier: Programming Language :: Python :: 3.9
Classifier: Programming Language :: Python :: 3.10
Classifier: Programming Language :: Python :: 3.11
Classifier: Natural Language :: English
